contraction_fix/__init__.py
contraction_fix/fixer.py
contraction_fix/data/informal_contractions.json
contraction_fix/data/internet_slang.json
contraction_fix/data/standard_contractions.json
contraction_fix-0.2.2.dist-info/licenses/LICENSE
contraction_fix-0.2.2.dist-info/METADATA
contraction_fix-0.2.2.dist-info/WHEEL
contraction_fix-0.2.2.dist-info/top_level.txt
contraction_fix-0.2.2.dist-info/RECORD
